README.rst
setup.cfg
setup.py
PySteamWeb.egg-info/PKG-INFO
PySteamWeb.egg-info/SOURCES.txt
PySteamWeb.egg-info/dependency_links.txt
PySteamWeb.egg-info/requires.txt
PySteamWeb.egg-info/top_level.txt
pysteamweb/__init__.py
pysteamweb/_steam_id_parser.py
pysteamweb/steam_base.py
pysteamweb/plugins/__init__.py
pysteamweb/plugins/chat.py
pysteamweb/plugins/mobile.py
pysteamweb/plugins/trade.py