Metadata-Version: 1.0
Name: PySteamWeb
Version: 1.1.0
Summary: python3 steam web login async
Home-page: https://github.com/patryk4815/PySteamWeb
Author: Patryk Sondej
Author-email: patryk.sondej@gmail.com
License: MIT
Keywords: python3,steam,login,api,async,aiohttp,asyncio,asynchronous
Platform: Posix; MacOS X; Windows
